README.rst
setup.py
blogger2puput/__init__.py
blogger2puput/management/__init__.py
blogger2puput/management/commands/__init__.py
blogger2puput/management/commands/blogger2puput.py
blogger_to_puput.egg-info/PKG-INFO
blogger_to_puput.egg-info/SOURCES.txt
blogger_to_puput.egg-info/dependency_links.txt
blogger_to_puput.egg-info/requires.txt
blogger_to_puput.egg-info/top_level.txt