Metadata-Version: 1.1
Name: blogger-to-puput
Version: 0.1
Summary: Import your Blogger blog data into Puput.
Home-page: http://github.com/APSL/blogger-to-puput
Author: David Valera
Author-email: david.valera.martinez@gmail.com
License: UNKNOWN
Keywords: django wagtail puput blog cms blogger
Platform: UNKNOWN
Classifier: Environment :: Web Environment
Classifier: Framework :: Django
Classifier: Intended Audience :: Developers
Classifier: Programming Language :: Python
Classifier: Programming Language :: Python :: 2
Classifier: Programming Language :: Python :: 2.7
Classifier: Programming Language :: Python :: 3
Classifier: Programming Language :: Python :: 3.3
Classifier: Programming Language :: Python :: 3.4
Classifier: Operating System :: OS Independent
Classifier: Topic :: Software Development
